MANIFEST.in
README.md
requirements.txt
setup.py
kivycharts/__init__.py
kivycharts/bar.py
kivycharts/chart.py
kivycharts/chart2d.py
kivycharts/geometry.py
kivycharts/line.py
kivycharts/pie.py
kivycharts/version.py
kivycharts.egg-info/PKG-INFO
kivycharts.egg-info/SOURCES.txt
kivycharts.egg-info/dependency_links.txt
kivycharts.egg-info/requires.txt
kivycharts.egg-info/top_level.txt
test/tgraph.py