Metadata-Version: 2.1
Name: kivycharts
Version: 0.0.9
Summary: kivy charts is a tool to build kivy data plot
Author: yumoqing
Author-email: yumoqing@icloud.com
License: UNKNOWN
Platform: any
Classifier: Development Status :: 3 - Alpha
Classifier: Operating System :: OS Independent
Classifier: Programming Language :: Python :: 3.5
Classifier: Topic :: Software Development :: Libraries :: Python Modules
